bigsimr/__init__.py
bigsimr/setup.py
bigsimr-0.1.0.dist-info/LICENSE
bigsimr-0.1.0.dist-info/METADATA
bigsimr-0.1.0.dist-info/WHEEL
bigsimr-0.1.0.dist-info/top_level.txt
bigsimr-0.1.0.dist-info/RECORD
