Metadata-Version: 2.1
Name: bigsimr
Version: 0.1.0
Summary: Simulate high-dimensional multivariate data with arbitrary marginal distributions
Home-page: https://github.com/SchisslerGroup/python-bigsimr
Author: Alex Knudson
Author-email: aknudson@nevada.unr.edu
License: UNKNOWN
Project-URL: Bug Tracker, https://github.com/SchisslerGroup/python-bigsimr/issues
Platform: UNKNOWN
Classifier: Programming Language :: Python :: 3
Classifier: License :: OSI Approved :: MIT License
Classifier: Operating System :: OS Independent
Requires-Python: >=3.6
Requires-Dist: numpy (>=1.19)
Requires-Dist: julia (>=0.5.6)
